llama_index/llms/gaudi/__init__.py
llama_index/llms/gaudi/base.py
llama_index/llms/gaudi/utils.py
llama_index_llms_gaudi-0.3.1.dist-info/METADATA
llama_index_llms_gaudi-0.3.1.dist-info/WHEEL
llama_index_llms_gaudi-0.3.1.dist-info/licenses/LICENSE
llama_index_llms_gaudi-0.3.1.dist-info/RECORD
