Metadata-Version: 2.4
Name: llama-index-llms-gaudi
Version: 0.3.1
Summary: llama-index llms gaudi integration
Author-email: Your Name <you@example.com>
License-Expression: MIT
License-File: LICENSE
Requires-Python: <4.0,>=3.9
Requires-Dist: huggingface-hub>=0.23.0
Requires-Dist: llama-index-core<0.15,>=0.13.0
Requires-Dist: llama-index-llms-huggingface<0.7,>=0.6.0
Requires-Dist: optimum[habana]>=1.21.2
Requires-Dist: torch<3,>=2.1.2
Requires-Dist: transformers[torch]<5,>=4.37.0
